lsb_release_ex.py
setup.py
lsb_release_ex.egg-info/PKG-INFO
lsb_release_ex.egg-info/SOURCES.txt
lsb_release_ex.egg-info/dependency_links.txt
lsb_release_ex.egg-info/top_level.txt