Metadata-Version: 1.1
Name: lsb-release-ex
Version: 0.1
Summary: Ehanced Linux Standard Base version reporting module
Home-page: https://github.com/likema/lsb_release_ex
Author: Like Ma
Author-email: likemartinma@gmail.com
License: GPLv2
Download-URL: https://github.com/likema/lsb_release_ex/archive/master.zip
Platform: UNKNOWN
Classifier: Topic :: Software Development :: Libraries :: Python Modules
Classifier: Programming Language :: Python
Classifier: Operating System :: POSIX :: Linux
Classifier: Intended Audience :: Developers
Classifier: License :: OSI Approved :: GNU General Public License v2 (GPLv2)
